README.md
setup.py
examples/__init__.py
examples/ag_news/__init__.py
examples/ag_news/binary.py
examples/ag_news/semantic.py
tests/__init__.py
tests/test_data_corruption.py
tests/test_label_encoder.py
tests/test_model_training.py
yafal/__init__.py
yafal/corruption.py
yafal/exceptions.py
yafal/label.py
yafal/models.py
yafal.egg-info/PKG-INFO
yafal.egg-info/SOURCES.txt
yafal.egg-info/dependency_links.txt
yafal.egg-info/requires.txt
yafal.egg-info/top_level.txt
yafal/regression/__init__.py
yafal/regression/binary.py
yafal/regression/semantic.py