Metadata-Version: 2.1
Name: yafal
Version: 1.0.1
Summary: Identification of Fake Labels using Large Model embeddings
Home-page: https://yafal.llinguai.eus
Author: Manex Serras
Author-email: mserras001@gmail.com
License: UNKNOWN
Keywords: Natural Language Processing,Artificial Intelligence,Fake Label detection,Deep Learning
Platform: UNKNOWN
Classifier: Programming Language :: Python :: 3
Classifier: License :: OSI Approved :: MIT License
Classifier: Operating System :: OS Independent
Requires-Python: >=3.8
